LICENSE
MANIFEST.in
README.md
setup.py
communitytopic/CommunityTopic.py
communitytopic/PreProcessing.py
communitytopic/__init__.py
communitytopic.egg-info/PKG-INFO
communitytopic.egg-info/SOURCES.txt
communitytopic.egg-info/dependency_links.txt
communitytopic.egg-info/requires.txt
communitytopic.egg-info/top_level.txt
communitytopic/test/__init__.py