Metadata-Version: 2.1
Name: communitytopic
Version: 0.1
Summary: Community Topic - Topic Modelling Method
Home-page: https://github.com/shr1911/communitytopic
Author: Shraddha Makwana
Author-email: smakwana@ualberta.ca
Classifier: Programming Language :: Python :: 3
Classifier: License :: OSI Approved :: MIT License
Classifier: Operating System :: OS Independent
Requires-Python: >=3.6
License-File: LICENSE
